fast_feature/__init__.py
fast_feature/dataframe_checks.py
fast_feature/py.typed
fast_feature/tags.py
quick_feature/__init__.py
quick_feature/dataframe_checks.py
quick_feature/py.typed
quick_feature/tags.py
quick_feature-0.0.1.dev0.dist-info/METADATA
quick_feature-0.0.1.dev0.dist-info/WHEEL
quick_feature-0.0.1.dev0.dist-info/top_level.txt
quick_feature-0.0.1.dev0.dist-info/RECORD
